hubview/__init__.py
hubview/app.py
hubview/demo/code.py
hubview/demo/lib/subpy.py
hubview/scripting/__init__.py
hubview/scripting/demo_script.py
hubview/scripting/script_server.py
hubview/static/scripts.js
hubview/static/styles.css
hubview/templates/base.html
hubview/templates/browse.html
hubview/templates/script.html
hubview/templates/script_og.html
hubview/templates/scripts_home.html
hubview/templates/view_file.html
hubview-0.8.dist-info/licenses/LICENSE
hubview-0.8.dist-info/METADATA
hubview-0.8.dist-info/WHEEL
hubview-0.8.dist-info/entry_points.txt
hubview-0.8.dist-info/top_level.txt
hubview-0.8.dist-info/RECORD
