Metadata-Version: 2.4
Name: hubview
Version: 0.8
Summary: GitHub-like local file viewer built with Flask
Author-email: Grey Liedtke <grey.liedtke@gmail.com>
License: MIT
License-File: LICENSE
Requires-Dist: flask>=3.0
Requires-Dist: markdown>=3.6
Requires-Dist: pymdown-extensions>=10.8
Requires-Dist: beautifulsoup4>=4.12
Requires-Dist: pandas==2.3.2
Requires-Dist: MarkupSafe==3.0.2
Requires-Dist: Werkzeug==3.1.3
Dynamic: license-file
